my_package/__init__.py
my_package/cli.py
my_package/utils.py
typer_package-0.1.0.dist-info/METADATA
typer_package-0.1.0.dist-info/WHEEL
typer_package-0.1.0.dist-info/entry_points.txt
typer_package-0.1.0.dist-info/top_level.txt
typer_package-0.1.0.dist-info/RECORD
