Metadata-Version: 2.4
Name: typer-package
Version: 0.1.0
Summary: An example typer package
Requires-Python: >=3.12
Requires-Dist: typer>=0.15.3
